microkanren/__init__.py
microkanren/cons.py
microkanren/core.py
microkanren/fd.py
microkanren/goals.py
microkanren/utils.py
microkanren-0.4.4.dist-info/METADATA
microkanren-0.4.4.dist-info/WHEEL
microkanren-0.4.4.dist-info/licenses/LICENSE
microkanren-0.4.4.dist-info/RECORD
