Metadata-Version: 2.1
Name: microkanren
Version: 0.4.4
Summary: A Python implementation of microkanren extended with constraints
Project-URL: Homepage, https://github.com/jams2/microkanren
Project-URL: Bug Tracker, https://github.com/jams2/microkanren/issues
Author-email: Joshua Munn <public@elysee-munn.family>
License: MIT License
License-File: LICENSE
Classifier: Development Status :: 2 - Pre-Alpha
Classifier: License :: OSI Approved :: MIT License
Classifier: Operating System :: OS Independent
Classifier: Programming Language :: Python :: 3
Classifier: Programming Language :: Python :: 3.11
Classifier: Programming Language :: Python :: 3.12
Requires-Python: <3.13,>=3.11
Requires-Dist: fastcons==0.4.1
Requires-Dist: immutables<1,>=0.19
Requires-Dist: pyrsistent<1,>=0.19
Provides-Extra: build
Requires-Dist: hatch==1.7.0; extra == 'build'
Provides-Extra: dev
Requires-Dist: ruff==0.1.2; extra == 'dev'
Provides-Extra: testing
Requires-Dist: pytest-profiling==1.7.0; extra == 'testing'
Requires-Dist: pytest==7.2.2; extra == 'testing'
Requires-Dist: tox==4.11.3; extra == 'testing'
